{
  "2018": {
    "year": 2018,
    "event": "All Things Assessment: Tools and Tips for Improving Program Outcomes",
    "start-date": "2018-04-27T06:00:00.000Z",
    "end-date": "2018-04-27T06:00:00.000Z",
    "location": "Library 21c",
    "address": "1175 Chapel Hills Drive ",
    "city-state-zipcode": "Colorado Springs, CO 80920",
    "phone": "(719) 884-9800",
    "website": "https://ppld.org/library-21c",
    "hotel": "Drury Inn & Suites",
    "hotel-address": "1170 InterQuest Parkway",
    "hotel-city-state-zipcode": "Colorado Springs, CO 80921",
    "reservations-phone": "1-800-325-0720",
    "reservations-online": "https://www.druryhotels.com/",
    "reservations-id": 2333924,
    "price-1-title": "Assessment training",
    "price-1": "Free",
    "price-2-title": "Mini Conference",
    "price-2": 50,
    "price-membership": 30,
    "registration-notes": "Assessment training registration closes: Friday, March 30, 2018",
    "register-online": "https://squareup.com/store/caepa",
    "register-mail": "1332 Marigold Ct. Lafayette, CO 80026",
    "era": "CAEPA"
  },
  "2016": {
    "year": 2016,
    "event": "Empowering Learners through Partnerships and Innovation",
    "start-date": "2016-10-13T06:00:00.000Z",
    "end-date": "2016-10-14T06:00:00.000Z",
    "location": "Westin Westminster",
    "address": "10600 Westminster Blvd",
    "city-state-zipcode": "Westminster, CO 80020",
    "phone": "(303) 410-5000",
    "website": "http://www.starwoodhotels.com/westin/property/overview/index.html?propertyID=1173",
    "hotel": "Westin Westminster",
    "hotel-address": "10600 Westminster Blvd",
    "hotel-city-state-zipcode": "Westminster, CO 80020",
    "reservations-phone": "(303) 410-5000",
    "reservations-online": "https://www.starwoodmeeting.com/events/start.action?id=1511022308&key=300336A7",
    "reservations-id": "CAEPA",
    "discount-title": "Early bird",
    "discount-expire": "2016-10-01T06:00:00.000Z",
    "price-1-title": "Single day",
    "price-1-discount": 100,
    "price-1": 150,
    "price-2-title": "Full registration",
    "price-2-discount": 150,
    "price-2": 200,
    "price-3-title": "Lunch only",
    "price-3-discount": 30,
    "price-3": 30,
    "price-membership": 30,
    "registration-notes": "Single day and full registration include membership dues",
    "register-online": "https://squareup.com/store/caepa",
    "register-mail": "1332 Marigold Ct. Lafayette, CO 80026",
    "era": "CAEPA"
  },
  "2015": {
    "year": 2015,
    "event": "Moving Forward with Innovation, Opportunity, and Action",
    "start-date": "2015-10-23T06:00:00.000Z",
    "end-date": "2015-10-24T06:00:00.000Z",
    "location": "Westin Westminster",
    "address": "10600 Westminster Blvd",
    "city-state-zipcode": "Westminster, CO 80020",
    "phone": "(303) 410-5000",
    "website": "http://www.starwoodhotels.com/westin/property/overview/index.html?propertyID=1173",
    "hotel": "Westin Westminster",
    "hotel-address": "10600 Westminster Blvd",
    "hotel-city-state-zipcode": "Westminster, CO 80020",
    "reservations-phone": "(303) 410-5000",
    "reservations-online": "https://www.starwoodmeeting.com/StarGroupsWeb/res?id=1405194525&key=173A4AC",
    "reservations-id": "CAEPA",
    "discount-title": "Early bird",
    "discount-expire": "2015-10-01T06:00:00.000Z",
    "price-1-title": "Single day",
    "price-1-discount": 75,
    "price-1": 125,
    "price-2-title": "Full registration",
    "price-2-discount": 100,
    "price-2": 175,
    "price-3-title": "Lunch only",
    "price-3-discount": 30,
    "price-3": 30,
    "price-membership": 30,
    "registration-notes": "Single day and full registration include membership dues",
    "register-online": "https://squareup.com/store/caepa",
    "register-mail": "1332 Marigold Ct. Lafayette, CO 80026",
    "program-path": "http://goo.gl/oO8mtT",
    "era": "CAEPA"
  },
  "2014": {
    "year": 2014,
    "event": "Hosted COABE National Conference in Denver",
    "start-date": "2015-04-21T06:00:00.000Z",
    "end-date": "2015-04-24T06:00:00.000Z",
    "location": "Hyatt Regency Denver at Colorado Convention Center",
    "address": "650 15th St",
    "city-state-zipcode": "Denver, CO 80202",
    "phone": "(303) 436-1234",
    "website": "https://denver.regency.hyatt.com/en/hotel/home.html",
    "hotel": "Hyatt Regency Denver at Colorado Convention Center",
    "hotel-address": "650 15th St",
    "hotel-city-state-zipcode": "Denver, CO 80202",
    "reservations-phone": "(303) 436-1234",
    "price-membership": 30,
    "registration-notes": "Single day and full registration include membership dues",
    "era": "CAEPA"
  },
  "2013": {
    "year": 2013,
    "event": "Adult Education: Imagine the Possibilities",
    "start-date": "2013-10-18T06:00:00.000Z",
    "end-date": "2013-10-09T06:00:00.000Z",
    "location": "The Antlers Hilton",
    "address": "4 S Cascade Ave",
    "city-state-zipcode": "Colorado Springs, CO 80903",
    "phone": "(719) 955-5600",
    "website": "http://antlers.com/",
    "hotel": "The Antlers Hilton",
    "hotel-address": "4 S Cascade Ave",
    "hotel-city-state-zipcode": "Colorado Springs, CO 80903",
    "reservations-phone": "(719) 955-5600",
    "era": "CAEPA"
  },
  "2012": {
    "year": 2012,
    "event": "Gearing Up for Change",
    "start-date": "2012-10-12T06:00:00.000Z",
    "end-date": "2012-10-13T06:00:00.000Z",
    "location": "Omni Interlocken Resort",
    "address": "500 Interlocken Blvd",
    "city-state-zipcode": "Broomfield, CO 80021",
    "phone": "(303) 438-6600",
    "website": "https://www.omnihotels.com/hotels/denver-interlocken",
    "hotel": "Omni Interlocken Resort",
    "hotel-address": "500 Interlocken Blvd",
    "hotel-city-state-zipcode": "Broomfield, CO 80021",
    "reservations-phone": "(303) 438-6600",
    "era": "CAEPA"
  },
  "2011": {
    "year": 2011,
    "event": "Maximizing Resources in Challenging Times",
    "start-date": "2011-10-21T06:00:00.000Z",
    "end-date": "2011-10-22T06:00:00.000Z",
    "location": "Marriott Denver Tech Center",
    "address": "4900 S Syracuse St",
    "city-state-zipcode": "Denver, CO 80237",
    "phone": "(303) 779-1100",
    "website": "https://www.denvermarriotttechcenter.com/",
    "hotel": "Marriott Denver Tech Center",
    "hotel-address": "4900 S Syracuse St",
    "hotel-city-state-zipcode": "Denver, CO 80237",
    "reservations-phone": "(303) 779-1100",
    "price-1-title": "Single day",
    "price-1": 115,
    "price-2-title": "Full registration",
    "price-2": 195,
    "era": "CAEPA"
  },
  "2010": {
    "year": 2010,
    "event": "The Power of Adult Learning",
    "start-date": "2010-10-22T06:00:00.000Z",
    "end-date": "2010-10-23T06:00:00.000Z",
    "location": "Marriott Denver Tech Center",
    "address": "4900 S Syracuse St",
    "city-state-zipcode": "Denver, CO 80237",
    "phone": "(303) 779-1100",
    "website": "https://www.denvermarriotttechcenter.com/",
    "hotel": "Marriott Denver Tech Center",
    "hotel-address": "4900 S Syracuse St",
    "hotel-city-state-zipcode": "Denver, CO 80237",
    "reservations-phone": "(303) 779-1100",
    "price-2-title": "Full registration",
    "price-2": 195,
    "era": "CAEPA"
  },
  "2009": {
    "year": 2009,
    "event": "Adult Education: Partnering for a Better Colorado",
    "start-date": "2009-08-05T06:00:00.000Z",
    "end-date": "2009-08-07T06:00:00.000Z",
    "location": "Beaver Run Resort",
    "address": "620 Village Rd",
    "city-state-zipcode": "Breckenridge, CO 80424",
    "phone": "(970) 453-6000",
    "website": "http://www.beaverrun.com/",
    "hotel": "Beaver Run Resort",
    "hotel-address": "620 Village Rd",
    "hotel-city-state-zipcode": "Breckenridge, CO 80424",
    "reservations-phone": "(970) 453-6000",
    "price-2-title": "Full registration",
    "price-2": 180,
    "era": "CAEPA"
  },
  "2008": {
    "year": 2008,
    "event": "Sharing Success: Adult Learners in Transition",
    "start-date": "2008-03-08T07:00:00.000Z",
    "end-date": "2008-03-10T06:00:00.000Z",
    "location": "Sheraton Denver West",
    "address": "360 Union Blvd",
    "city-state-zipcode": "Lakewood, CO 80228",
    "phone": "(303) 987-2000",
    "website": "http://www.sheratondenverwest.com/",
    "hotel": "Sheraton Denver West",
    "hotel-address": "360 Union Blvd",
    "hotel-city-state-zipcode": "Lakewood, CO 80228",
    "reservations-phone": "(303) 987-2000",
    "era": "CAEPA"
  },
  "2007": {
    "year": 2007,
    "event": "Engaging Diverse Learners",
    "start-date": "2007-02-07T07:00:00.000Z",
    "end-date": "2007-02-09T07:00:00.000Z",
    "location": "Omni Interlocken Resort",
    "address": "500 Interlocken Blvd",
    "city-state-zipcode": "Broomfield, CO 80021",
    "phone": "(303) 438-6600",
    "website": "https://www.omnihotels.com/hotels/denver-interlocken",
    "hotel": "Omni Interlocken Resort",
    "hotel-address": "500 Interlocken Blvd",
    "hotel-city-state-zipcode": "Broomfield, CO 80021",
    "reservations-phone": "(303) 438-6600",
    "era": "CAEPA"
  },
  "2006": {
    "year": 2006,
    "event": "Leading Learners to a Higher Level",
    "start-date": "2006-04-26T06:00:00.000Z",
    "end-date": "2006-04-29T06:00:00.000Z",
    "location": "Adams Mark Hotel",
    "address": "1550 Court Place",
    "city-state-zipcode": "Denver, CO 80202",
    "hotel": "Adams Mark Hotel",
    "hotel-address": "1550 Court Place",
    "hotel-city-state-zipcode": "Denver, CO 80202",
    "price-2-title": "Full registration",
    "price-2": 245,
    "era": "CAEPA"
  },
  "2005": {
    "year": 2005,
    "era": "CAEPA"
  },
  "2004": {
    "year": 2004,
    "era": "CAEPA"
  },
  "2003": {
    "year": 2003,
    "era": "CAEPA"
  },
  "2002": {
    "year": 2002,
    "era": "CAEPA"
  },
  "2001": {
    "year": 2001,
    "event": "HAL (Helping Adults Learn) 2001: A Mind Odyssey",
    "start-date": "2001-04-20T06:00:00.000Z",
    "end-date": "2001-04-20T06:00:00.000Z",
    "location": "Red Rock Community College",
    "address": "13300 W 6th Ave",
    "city-state-zipcode": "Lakewood, CO 80228",
    "phone": "(303) 914-6600",
    "website": "http://www.rrcc.edu/",
    "price-2-title": "Full registration",
    "price-2": 95,
    "era": "CAEPA"
  },
  "1999": {
    "year": 1999,
    "event": "Prospecting for Gold in the 21st Century",
    "start-date": "1999-10-28T06:00:00.000Z",
    "end-date": "1999-10-29T06:00:00.000Z",
    "location": "Garden of the Gods",
    "address": "1805 N 30th St",
    "city-state-zipcode": "Colorado Springs, CO 80904",
    "phone": "(719) 634-6666",
    "website": "http://gardenofgods.com/",
    "era": "CAEPA"
  },
  "1998": {
    "year": 1998,
    "event": "The Rendezvous at Beaver Creek: A Renewal of Mind, Body, and Spirit",
    "start-date": "1998-05-02T06:00:00.000Z",
    "end-date": "1998-05-02T06:00:00.000Z",
    "city-state-zipcode": "Beaver Creek, CO 81620",
    "website": "http://www.beavercreek.com/",
    "era": "CAEPA"
  },
  "1997": {
    "year": 1997,
    "era": "CACAE"
  },
  "1996": {
    "year": 1996,
    "event": "Learning and Growing Together",
    "start-date": "1996-10-18T06:00:00.000Z",
    "end-date": "1996-10-19T06:00:00.000Z",
    "location": "Regency Hotel",
    "address": "3900 Elati St",
    "city-state-zipcode": "Denver, CO 80216",
    "era": "CACAE"
  },
  "1995": {
    "year": 1995,
    "event": "New Pathways to Program Success",
    "start-date": "1995-09-21T06:00:00.000Z",
    "end-date": "1995-09-22T06:00:00.000Z",
    "location": "Tower Executive",
    "address": "1406 Curtis Street",
    "city-state-zipcode": "Denver, CO 80203",
    "phone": "(303) 571-0301",
    "website": "http://thecurtis.com/",
    "price-2-title": "Full registration",
    "price-2": 90,
    "price-membership": 15,
    "era": "CACAE"
  },
  "1994": {
    "year": 1994,
    "event": "Building Learning Communities",
    "start-date": "1994-09-29T06:00:00.000Z",
    "end-date": "1994-09-30T06:00:00.000Z",
    "location": "Ramada Inn",
    "city-state-zipcode": "Denver, CO",
    "price-2-title": "Full registration",
    "price-2": 80,
    "price-membership": 15,
    "era": "CACAE"
  },
  "1993": {
    "year": 1993,
    "event": "Proactive Skills in the 90's for Adult and Community Educators",
    "start-date": "1993-10-28T06:00:00.000Z",
    "end-date": "1993-10-29T06:00:00.000Z",
    "location": "Embassy Suites by Hilton Colorado Springs",
    "address": "7290 Commerce Center Dr",
    "city-state-zipcode": "Colorado Springs, CO 80919",
    "phone": "(719) 599-9100",
    "website": "http://embassysuites3.hilton.com/en/hotels/colorado/embassy-suites-by-hilton-colorado-springs-COSCCES/index.html",
    "price-2-title": "Full registration",
    "price-2": 80,
    "price-membership": 15,
    "era": "CACAE"
  },
  "1992": {
    "year": 1992,
    "event": "Colorado Collaborates, Designing Solutions for the Future",
    "start-date": "1992-10-01T06:00:00.000Z",
    "end-date": "1992-10-02T06:00:00.000Z",
    "location": "Embassy Suites by Hilton Colorado Springs",
    "address": "7290 Commerce Center Dr",
    "city-state-zipcode": "Colorado Springs, CO 80919",
    "phone": "(719) 599-9100",
    "website": "http://embassysuites3.hilton.com/en/hotels/colorado/embassy-suites-by-hilton-colorado-springs-COSCCES/index.html",
    "price-2-title": "Full registration",
    "price-2": 85,
    "price-membership": 15,
    "era": "CACAE"
  },
  "1991": {
    "year": 1991,
    "event": "Professional Power from the Inside Out",
    "start-date": "1991-10-02T06:00:00.000Z",
    "end-date": "1991-10-04T06:00:00.000Z",
    "location": "Hyatt Regency Denver Tech Center",
    "address": "7800 E Tufts Ave",
    "city-state-zipcode": "Denver, CO 80237",
    "phone": "(303) 779-1234",
    "website": "http://denvertechcenter.regency.hyatt.com/en/hotel/home.html",
    "price-2-title": "Full registration",
    "price-2": 95,
    "era": "CACAE"
  },
  "1990": {
    "year": 1990,
    "event": "Winning Strategies for Adult in the 1990's",
    "start-date": "1990-09-20T06:00:00.000Z",
    "end-date": "1990-09-22T06:00:00.000Z",
    "location": "Fort Collins Marriott",
    "address": "50 E Horsetooth Rd",
    "city-state-zipcode": "Fort Collins, CO 80525",
    "phone": "(970) 226-5200",
    "website": "http://www.marriott.com/hotels/travel/ftcco-fort-collins-marriott/",
    "price-2-title": "Full registration",
    "price-2": 70,
    "era": "CACAE"
  },
  "1989": {
    "year": 1989,
    "event": "Providing Leadership in the 1990's",
    "start-date": "1989-09-22T06:00:00.000Z",
    "end-date": "1989-09-23T06:00:00.000Z",
    "location": "Hyatt Regency Denver Tech Center",
    "address": "7800 E Tufts Ave",
    "city-state-zipcode": "Denver, CO 80237",
    "phone": "(303) 779-1234",
    "website": "http://denvertechcenter.regency.hyatt.com/en/hotel/home.html",
    "price-2-title": "Full registration",
    "price-2": 60,
    "price-membership": 15,
    "era": "CACAE"
  },
  "1988": {
    "year": 1988,
    "event": "Colorado’s Future: A Learning Society",
    "start-date": "1988-10-06T06:00:00.000Z",
    "end-date": "1988-10-08T06:00:00.000Z",
    "location": "Red Lion Hotel",
    "address": "314 W Bijou St",
    "city-state-zipcode": "Colorado Springs, CO 80905",
    "price-2-title": "Full registration",
    "price-2": 75,
    "price-membership": 10,
    "era": "CACAE"
  },
  "1987": {
    "year": 1987,
    "event": "Ad-Venture Beyond Yourself",
    "start-date": "1987-09-25T06:00:00.000Z",
    "end-date": "1987-09-27T06:00:00.000Z",
    "location": "Iron Horse Resort",
    "address": "101 Iron Horse Way",
    "city-state-zipcode": "Winter Park, CO 80482",
    "phone": "(970) 726-8851",
    "price-2-title": "Full registration",
    "price-2": 65,
    "price-membership": 10,
    "era": "CACAE"
  },
  "1986": {
    "year": 1986,
    "event": "Keys to Excellence, ’87 and Beyond",
    "start-date": "1986-09-25T06:00:00.000Z",
    "end-date": "1986-09-27T06:00:00.000Z",
    "location": "Fort Collins Marriott",
    "address": "350 E Horsetooth Rd",
    "city-state-zipcode": "Denver, CO",
    "phone": "(970) 226-5200",
    "website": "http://www.marriott.com/hotels/travel/ftcco-fort-collins-marriott/",
    "price-2-title": "Full registration",
    "price-2": 75,
    "price-membership": 10,
    "era": "CACAE"
  },
  "1985": {
    "year": 1985,
    "event": "Partners for Lifelong Learning",
    "start-date": "1985-10-10T06:00:00.000Z",
    "end-date": "1985-10-12T06:00:00.000Z",
    "location": "Regency Hotel",
    "address": "3900 Elati St",
    "city-state-zipcode": "Denver, CO 80216",
    "era": "CACAE"
  },
  "1984": {
    "year": 1984,
    "event": "The Winning Edge",
    "start-date": "1984-10-18T06:00:00.000Z",
    "end-date": "1984-10-19T06:00:00.000Z",
    "location": "Beaver Run Resort & Conference Center",
    "address": "620 Village Rd",
    "city-state-zipcode": "Breckenridge, CO 80424",
    "phone": "(970) 453-6000",
    "website": "http://www.beaverrun.com/",
    "price-2-title": "Full registration",
    "price-2": 65,
    "price-membership": 10,
    "era": "CACAE"
  },
  "1983": {
    "year": 1983,
    "event": "Out of Many - One",
    "start-date": "1983-10-20T06:00:00.000Z",
    "end-date": "1983-10-22T06:00:00.000Z",
    "location": "The Westin Riverfront Resort & Spa at Beaver Creek Mountain",
    "address": "126 Riverfront Ln",
    "city-state-zipcode": "Avon, CO 81620",
    "phone": "(970) 790-6000",
    "website": "http://www.westinriverfrontbeavercreek.com/",
    "price-2-title": "Full registration",
    "price-2": 55,
    "price-membership": 10,
    "era": "CACAE"
  },
  "1982": {
    "year": 1982,
    "event": "Joining Hands for the Future - Networking for Survival",
    "start-date": "1982-09-29T06:00:00.000Z",
    "end-date": "1982-09-29T06:00:00.000Z",
    "location": "Sheraton Inn",
    "city-state-zipcode": "Colorado Springs, CO",
    "era": "CACAE"
  },
  "1981": {
    "year": 1981,
    "event": "Untitled",
    "start-date": "1981-10-01T06:00:00.000Z",
    "end-date": "1981-10-02T06:00:00.000Z",
    "location": "Falcon Inn",
    "address": "1865 Woodmoor Dr",
    "city-state-zipcode": "Monument, CO 80132",
    "price-membership": 10,
    "era": "CACAE"
  },
  "1980": {
    "year": 1980,
    "event": "Steps to Tomorrow",
    "start-date": "1980-10-02T06:00:00.000Z",
    "end-date": "1980-10-03T06:00:00.000Z",
    "location": "Falcon Inn",
    "address": "1865 Woodmoor Dr",
    "city-state-zipcode": "Monument, CO 80132",
    "price-2-title": "Full registration",
    "price-2": 40,
    "price-membership": 0,
    "era": "CACAE"
  },
  "1979": {
    "year": 1979,
    "era": "CACAE"
  },
  "1978": {
    "year": 1978,
    "era": "CACAE"
  },
  "1977": {
    "year": 1977,
    "era": "CACAE"
  },
  "1976": {
    "year": 1976,
    "event": "Lifelong Learning - Come and See",
    "start-date": "1976-10-21T06:00:00.000Z",
    "end-date": "1976-10-22T06:00:00.000Z",
    "location": "Adult Education Center in Longmont",
    "city-state-zipcode": "Longmont, CO",
    "price-2-title": "Full registration",
    "price-2": 16,
    "price-membership": 5,
    "era": "CACAE"
  },
  "1975": {
    "year": 1975,
    "event": "CACAE Past Imperfect, Present Indicative, Future Tense",
    "start-date": "1975-10-16T06:00:00.000Z",
    "end-date": "1975-10-17T06:00:00.000Z",
    "location": "Ramada Inn",
    "city-state-zipcode": "Denver, CO",
    "price-2-title": "Full registration",
    "price-2": 35,
    "era": "CACAE"
  },
  "1974": {
    "year": 1974,
    "event": "Continuing Education - The Future",
    "start-date": "1974-10-10T06:00:00.000Z",
    "end-date": "1974-10-11T06:00:00.000Z",
    "location": "Colorado University",
    "city-state-zipcode": "Boulder, CO",
    "website": "http://www.colorado.edu/",
    "price-2-title": "Full registration",
    "price-2": 25,
    "era": "CACAE"
  },
  "1973": {
    "year": 1973,
    "era": "CACAE"
  },
  "1972": {
    "year": 1972,
    "event": "Seminar on Critical Consideration for Adult Educators in Colorado Communities",
    "start-date": "1972-11-30T07:00:00.000Z",
    "end-date": "1972-11-30T07:00:00.000Z",
    "location": "Colorado State University",
    "city-state-zipcode": "Fort Collins, CO 80523",
    "website": "http://www.colostate.edu/",
    "era": "CACAE"
  },
  "1971": {
    "year": 1971,
    "event": "Continuing Ed for the Total Community",
    "start-date": "1971-05-24T06:00:00.000Z",
    "end-date": "1971-05-24T06:00:00.000Z",
    "era": "CACAE"
  },
  "1970": {
    "year": 1970,
    "era": "CACAE"
  },
  "1969": {
    "year": 1969,
    "event": "An Umbrella Organization for Adult Ed in Colorado",
    "start-date": "1969-05-10T06:00:00.000Z",
    "end-date": "1969-05-10T06:00:00.000Z",
    "location": "Fort Collins",
    "city-state-zipcode": "Fort Collins, CO",
    "era": "CACAE"
  },
  "1968": {
    "year": 1968,
    "event": "CAPSAE / CCAE",
    "start-date": "1968-05-04T06:00:00.000Z",
    "end-date": "1968-05-04T06:00:00.000Z",
    "location": "Colorado University",
    "city-state-zipcode": "Boulder, CO",
    "era": "CAPSAE / CCAE"
  },
  "1967": {
    "year": 1967,
    "event": "CAPSAE / CCAE",
    "start-date": "1967-10-26T06:00:00.000Z",
    "end-date": "1967-10-27T06:00:00.000Z",
    "location": "Colorado Department of Education",
    "city-state-zipcode": "Denver, CO",
    "price-membership": 2,
    "era": "CAPSAE / CCAE"
  },
  "1966": {
    "year": 1966,
    "era": "CAPSAE / CCAE"
  },
  "1965": {
    "year": 1965,
    "event": "CAPSAE (Colorado Association of Public School Adult Educators)",
    "era": "CAPSAE / CCAE"
  },
  "1964": {
    "year": 1964,
    "event": "CCAE (Colorado Council of Adult Education)",
    "era": "CAPSAE / CCAE"
  },
  "1963": {
    "year": 1963,
    "era": "CAPSAE / CCAE"
  },
  "1962": {
    "year": 1962,
    "event": "Calvin Orr hired as Section Head for Adult Education in state Division of Education Beyond High School",
    "era": "CAPSAE / CCAE"
  },
  "1961": {
    "year": 1961,
    "era": "CAPSAE / CCAE"
  },
  "1960": {
    "year": 1960,
    "era": "CAPSAE / CCAE"
  },
  "1959": {
    "year": 1959,
    "era": "CAPSAE / CCAE"
  },
  "1958": {
    "year": 1958,
    "era": "CAPSAE / CCAE"
  },
  "1957": {
    "year": 1957,
    "era": "CAPSAE / CCAE"
  },
  "1956": {
    "year": 1956,
    "era": "CAPSAE / CCAE"
  },
  "1955": {
    "year": 1955,
    "event": "Roy Minnis, first Colorado State Director of Adult Education",
    "era": "CAPSAE / CCAE"
  },
  "1954": {
    "year": 1954,
    "era": "CAPSAE / CCAE"
  },
  "1953": {
    "year": 1953,
    "era": "CAPSAE / CCAE"
  },
  "1952": {
    "year": 1952,
    "era": "CAPSAE / CCAE"
  },
  "1951": {
    "year": 1951,
    "era": "CAPSAE / CCAE"
  },
  "1950": {
    "year": 1950,
    "era": "CAPSAE / CCAE"
  },
  "1949": {
    "year": 1949,
    "era": "CAPSAE / CCAE"
  },
  "1948": {
    "year": 1948,
    "era": "CAPSAE / CCAE"
  },
  "1947": {
    "year": 1947,
    "era": "CAPSAE / CCAE"
  },
  "1946": {
    "year": 1946,
    "era": "CAPSAE / CCAE"
  },
  "1945": {
    "year": 1945,
    "era": "CAPSAE / CCAE"
  },
  "1944": {
    "year": 1944,
    "era": "CAPSAE / CCAE"
  },
  "1943": {
    "year": 1943,
    "era": "CAPSAE / CCAE"
  },
  "1942": {
    "year": 1942,
    "era": "CAPSAE / CCAE"
  },
  "1941": {
    "year": 1941,
    "era": "CAPSAE / CCAE"
  },
  "1940": {
    "year": 1940,
    "era": "CAPSAE / CCAE"
  },
  "1939": {
    "year": 1939,
    "era": "CAPSAE / CCAE"
  },
  "1938": {
    "year": 1938,
    "era": "CAPSAE / CCAE"
  },
  "1937": {
    "year": 1937,
    "era": "CAPSAE / CCAE"
  },
  "1936": {
    "year": 1936,
    "era": "CAPSAE / CCAE"
  },
  "1935": {
    "year": 1935,
    "event": "Adult Education Council of Denver organized",
    "era": "CAPSAE / CCAE"
  }
}
